Urls34/__init__.py
Urls34/setup.py
Urls34-0.0.1.dist-info/METADATA
Urls34-0.0.1.dist-info/WHEEL
Urls34-0.0.1.dist-info/top_level.txt
Urls34-0.0.1.dist-info/RECORD
